[
  {
    "type": "schedule",
    "start": "0900",
    "end": "1130",
    "event_kr": "Jisu Makeup Trial",
    "note_kr": null,
    "event_en": "Jisu Makeup Trial",
    "note_en": "Eli & Dad at Gym",
    "ticket": null,
    "map": null,
    "more": null
  },
  {
    "type": "info",
    "start": "1000",
    "end": "1030",
    "event_kr": "🚊 Citizen M → White Boutik",
    "note_kr": "40분 예상",
    "event_en": "Citizen M → White Boutik",
    "note_en": "Estimated 40 minutes",
    "ticket": null,
    "map": "https://maps.app.goo.gl/JhBKUAPL7v7ugdJ67",
    "more": null
  },
  {
    "type": "schedule",
    "start": "1300",
    "end": "1330",
    "event_kr": "White Boutik",
    "note_kr": null,
    "event_en": "White Boutik",
    "note_en": null,
    "ticket": null,
    "map": null,
    "more": null
  },
  {
    "type": "schedule",
    "start": "1300",
    "end": "1330",
    "event_kr": "Champs-Élysées",
    "note_kr": null,
    "event_en": "Champs-Élysées",
    "note_en": null,
    "ticket": null,
    "map": null,
    "more": null
  },
  {
    "type": "schedule",
    "start": "1300",
    "end": "1330",
    "event_kr": "Palais de Chaillot",
    "note_kr": null,
    "event_en": "Palais de Chaillot",
    "note_en": null,
    "ticket": null,
    "map": "https://maps.app.goo.gl/Jt1uBYVacskPBrZt8",
    "more": null
  },
  {
    "type": "schedule",
    "start": "1300",
    "end": "1330",
    "event_kr": "Place du Trocadero",
    "note_kr": null,
    "event_en": "Place du Trocadero",
    "note_en": null,
    "ticket": null,
    "map": "https://maps.app.goo.gl/D47sR7U8M3rddvMB8",
    "more": null
  },
  {
    "type": "schedule",
    "start": "1300",
    "end": "1330",
    "event_kr": "les telephones AREA FOR THE DINNER",
    "note_kr": null,
    "event_en": "les telephones AREA FOR THE DINNER",
    "note_en": null,
    "ticket": null,
    "map": "https://maps.app.goo.gl/57EZt6YGGUEfDNop7",
    "more": null
  },
  {
    "type": "schedule",
    "start": "2000",
    "end": "2100",
    "event_kr": "Bateaux Parisiens",
    "note_kr": null,
    "event_en": "Bateaux Parisiens",
    "note_en": null,
    "ticket": null,
    "map": "https://maps.app.goo.gl/kQ8z7mymdegJhvou6",
    "more": null
  }
]
